foscat/BkBase.py
foscat/BkNumpy.py
foscat/BkTensorflow.py
foscat/BkTorch.py
foscat/CNN.py
foscat/CircSpline.py
foscat/FoCUS.py
foscat/GCNN.py
foscat/HOrientedConvol.py
foscat/HealBili.py
foscat/HealSpline.py
foscat/Plot.py
foscat/Softmax.py
foscat/SphericalStencil.py
foscat/Spline1D.py
foscat/Synthesis.py
foscat/UNET.py
foscat/__init__.py
foscat/alm.py
foscat/backend.py
foscat/backend_tens.py
foscat/heal_NN.py
foscat/healpix_unet_torch.py
foscat/healpix_vit_skip.py
foscat/healpix_vit_torch.py
foscat/loss_backend_tens.py
foscat/loss_backend_torch.py
foscat/planar_vit.py
foscat/scat.py
foscat/scat1D.py
foscat/scat2D.py
foscat/scat_cov.py
foscat/scat_cov1D.py
foscat/scat_cov2D.py
foscat/scat_cov_map.py
foscat/scat_cov_map2D.py
foscat/unet_2_d_from_healpix_params.py
foscat-2025.11.1.dist-info/licenses/LICENSE
foscat-2025.11.1.dist-info/METADATA
foscat-2025.11.1.dist-info/WHEEL
foscat-2025.11.1.dist-info/top_level.txt
foscat-2025.11.1.dist-info/RECORD
