Metadata-Version: 2.4
Name: foscat
Version: 2025.11.1
Summary: Generate synthetic Healpix or 2D data using Cross Scattering Transform
Author-email: Jean-Marc DELOUIS <jean.marc.delouis@ifremer.fr>
Maintainer-email: Theo Foulquier <theo.foulquier@ifremer.fr>
License: BSD-3-Clause
Project-URL: Repository, https://github.com/jmdelouis/FOSCAT.git
Project-URL: Issues, https://github.com/jmdelouis/FOSCAT/issues
Project-URL: Documentation, https://foscat-documentation.readthedocs.io/en/latest/index.html
Keywords: scattering transform,component separation,denoising
Classifier: Intended Audience :: Science/Research
Classifier: License :: OSI Approved :: MIT License
Classifier: Programming Language :: Python :: 3
Classifier: Programming Language :: Python :: 3.9
Classifier: Programming Language :: Python :: 3.10
Classifier: Programming Language :: Python :: 3.11
Classifier: Programming Language :: Python :: 3.12
Requires-Python: >=3.9
License-File: LICENSE
Requires-Dist: imageio
Requires-Dist: imagecodecs
Requires-Dist: matplotlib
Requires-Dist: numpy
Requires-Dist: healpy
Requires-Dist: spherical
Dynamic: license-file
